odoo/addons/event_registration_mail_compose/README.rst
odoo/addons/event_registration_mail_compose/__init__.py
odoo/addons/event_registration_mail_compose/__manifest__.py
odoo/addons/event_registration_mail_compose/i18n/es.po
odoo/addons/event_registration_mail_compose/i18n/event_registration_mail_compose.pot
odoo/addons/event_registration_mail_compose/i18n/fr.po
odoo/addons/event_registration_mail_compose/i18n/fr_FR.po
odoo/addons/event_registration_mail_compose/i18n/it.po
odoo/addons/event_registration_mail_compose/readme/CONTRIBUTORS.rst
odoo/addons/event_registration_mail_compose/readme/DESCRIPTION.rst
odoo/addons/event_registration_mail_compose/static/description/icon.png
odoo/addons/event_registration_mail_compose/static/description/index.html
odoo/addons/event_registration_mail_compose/views/event_registration.xml
odoo_addon_event_registration_mail_compose-15.0.1.0.0.11.dist-info/METADATA
odoo_addon_event_registration_mail_compose-15.0.1.0.0.11.dist-info/WHEEL
odoo_addon_event_registration_mail_compose-15.0.1.0.0.11.dist-info/top_level.txt
odoo_addon_event_registration_mail_compose-15.0.1.0.0.11.dist-info/RECORD
